 [
 	{"url":"/admin/sys/console/console.html","icon":"icon-dashboard","name":"工作台","id":"menu_console"},
 	{"url":"","icon":"icon-picture","name":"旅游景点","id":"menu_scenic_p","children":[
		{"url":"admin/sys/scenic/sys_scenic_type_table.html","icon":"icon-picture","name":"景点类型","id":"menu_scenic_type_table"},
		{"url":"admin/sys/scenic/sys_scenic_level_table.html","icon":"icon-picture","name":"景点星级","id":"menu_scenic_type_level"},
		{"url":"admin/sys/scenic/sys_scenic_ticket_type_table.html","icon":"icon-picture","name":"景点门票类型","id":"menu_scenic_ticket_type_table"},
	]},
	{"url":"","icon":"icon-road","name":"旅游路线","id":"menu_toursimline_p","children":[
	    {"url":"admin/sys/tourismline/sys_tourismline_type_table.html","icon":"icon-road","name":"线路类型","id":"menu_toursimline_type_table"},
	    {"url":"admin/sys/tourismline/sys_tourismline_theme_table.html","icon":"icon-road","name":"线路主题","id":"menu_toursimline_theme_table"},
	    {"url":"admin/sys/tourismline/sys_tourismline_property_table.html","icon":"icon-road","name":"线路性质","id":"menu_toursimline_property_table"},
	]},
	{"url":"","icon":"icon-building","name":"酒店管理","id":"menu_hotel_p","children":[
	    {"url":"admin/sys/hotel/sys_hotel_type_table.html","icon":"icon-building","name":"酒店类型","id":"menu_hotel_type_table"},
	    {"url":"admin/sys/hotel/sys_hotel_level_table.html","icon":"icon-building","name":"酒店星级","id":"menu_hotel_level_table"},
	    {"url":"admin/sys/hotel/sys_hotel_room_type_table.html","icon":"icon-building","name":"酒店房型","id":"menu_hotel_room_type_table"},
	]},
	{"url":"","icon":"icon-truck","name":"汽车租赁","id":"menu_car_p","children":[
	    {"url":"admin/sys/car/sys_car_brand_table.html","icon":"icon-truck","name":"汽车品牌","id":"menu_car_brand_table"},
	    {"url":"admin/sys/car/sys_car_type_table.html","icon":"icon-truck","name":"汽车类型","id":"menu_car_type_table"},
	]},
	{"url":"","icon":"icon-camera","name":"旅游设备","id":"menu_equipment_p","children":[
	    {"url":"admin/sys/equipment/sys_equipment_type_table.html","icon":"icon-camera","name":"设备类型","id":"menu_equipment_type_table"},
	]},
	{"url":"","icon":"icon-film","name":"广告管理","id":"menu_ads_p","children":[
	    {"url":"admin/sys/ads/sys_ads_text_table.html","icon":"icon-film","name":"文字广告","id":"menu_ads_text_table"},
	    {"url":"admin/sys/ads/sys_ads_picture_table.html","icon":"icon-film","name":"图片广告","id":"menu_ads_picture_table"},
	    {"url":"admin/sys/ads/sys_ads_position_table.html","icon":"icon-film","name":"广告位置","id":"menu_ads_position_table"},
	]},
	{"url":"","icon":"icon-globe","name":"新闻管理","id":"menu_news_p","children":[
	    {"url":"admin/sys/news/sys_news_table.html","icon":"icon-globe","name":"新闻列表","id":"menu_news_table"},
	    {"url":"admin/sys/news/sys_news_type_table.html","icon":"icon-globe","name":"新闻类型","id":"menu_news_type_table"},
	]},
	{"url":"","icon":"icon-plane","name":"机票预订","id":"menu_planticket_p","children":[
	    {"url":"admin/sys/planticket/sys_planticket_book_table.html","icon":"icon-plane","name":"机票预订链接","id":"menu_planticket_table"},
	]},
]